bthlabs_jsonrpc_django/__init__.py
bthlabs_jsonrpc_django/apps.py
bthlabs_jsonrpc_django/auth_checks.py
bthlabs_jsonrpc_django/codecs.py
bthlabs_jsonrpc_django/executor.py
bthlabs_jsonrpc_django/py.typed
bthlabs_jsonrpc_django/serializer.py
bthlabs_jsonrpc_django/views.py
bthlabs_jsonrpc_django-1.2.0.dist-info/LICENSE
bthlabs_jsonrpc_django-1.2.0.dist-info/METADATA
bthlabs_jsonrpc_django-1.2.0.dist-info/WHEEL
bthlabs_jsonrpc_django-1.2.0.dist-info/RECORD
