Metadata-Version: 2.1
Name: bthlabs-jsonrpc-django
Version: 1.2.0
Summary: BTHLabs JSONRPC - Django integration
Home-page: https://projects.bthlabs.pl/bthlabs-jsonrpc/
License: MIT
Author: Tomek Wójcik
Author-email: contact@bthlabs.pl
Maintainer: BTHLabs
Maintainer-email: contact@bthlabs.pl
Requires-Python: >=3.10,<4.0
Classifier: License :: OSI Approved :: MIT License
Classifier: Programming Language :: Python :: 3
Classifier: Programming Language :: Python :: 3.10
Classifier: Programming Language :: Python :: 3.11
Classifier: Programming Language :: Python :: 3.12
Requires-Dist: bthlabs-jsonrpc-core (==1.1.0)
Requires-Dist: django (>=4.2,<5.3)
Project-URL: Documentation, https://projects.bthlabs.pl/bthlabs-jsonrpc/aiohttp/
Project-URL: Repository, https://git.bthlabs.pl/tomekwojcik/bthlabs-jsonrpc/
